saythanks_cli.py
saythanks_cli-1.0.0a2.dist-info/DESCRIPTION.rst
saythanks_cli-1.0.0a2.dist-info/METADATA
saythanks_cli-1.0.0a2.dist-info/RECORD
saythanks_cli-1.0.0a2.dist-info/WHEEL
saythanks_cli-1.0.0a2.dist-info/entry_points.txt
saythanks_cli-1.0.0a2.dist-info/metadata.json
saythanks_cli-1.0.0a2.dist-info/top_level.txt
